<?xml version="1.0" encoding="utf-8"?>
<colormap xmlns:xsi="http://www.w3.org/2001/XMLSchema-instance" 
		xsi:noNamespaceSchemaLocation="../../../../../../schemas/colormap.xsd" >		
	
	<color index="00" red="032" green="016" blue="056" /> <!-- contours -->
	<color index="01" red="072" green="024" blue="096" /> <!-- corps très foncé -->
	<color index="02" red="102" green="066" blue="152" /> <!-- corps foncé -->
	<color index="03" red="185" green="131" blue="233" /> <!-- corps clair -->
	<color index="04" red="144" green="072" blue="208" /> <!-- corps normal -->
	<color index="05" red="224" green="192" blue="252" /> <!-- corps très clair -->
	<color index="09" red="238" green="226" blue="249" /> <!-- corps très très clair -->
	<color index="14" red="250" green="250" blue="250" /> <!-- reflets (blanc cassé) -->

</colormap>
