<?xml version="1.0" encoding="UTF-8"?>
<profiles xmlns:xsi="http://www.w3.org/2001/XMLSchema-instance" xsi:noNamespaceSchemaLocation="..\..\..\resources\schemas\profiles.xsd">
	<general last="50" />
	<list>
		<profile file="17" name="Şahin+Yıldırım" />
		<profile file="35" name="Demirağ+Şagar" />
		<profile file="18" name="Promeneur" />
		<profile file="36" name="Devecioğlu+Korkmaz" />
		<profile file="33" name="Çöremen+Küçükkarakürt" />
		<profile file="15" name="Kurtuluş+Özsoy" />
		<profile file="16" name="Okan+Yüksel" />
		<profile file="34" name="Dayioğlugil+Geçkalan" />
		<profile file="13" name="Keçer+Yaman" />
		<profile file="39" name="Kökciyan+Mazmanoğlu" />
		<profile file="14" name="Kılıç+Pala" />
		<profile file="11" name="Göksel+Mengeş" />
		<profile file="37" name="Erişik+Pektaş" />
		<profile file="38" name="Günalp+Yürtsever" />
		<profile file="12" name="Hanci+Toprak" />
		<profile file="41" name="Tırtıl+Tomruk" />
		<profile file="40" name="Medeni+Uluer" />
		<profile file="49" name="Promeneur 2" />
		<profile file="27" name="Adatepe" />
		<profile file="28" name="Akkaya+Danacioğlu" />
		<profile file="29" name="Akpolat+Şener" />
		<profile file="3" name="Baydar+Camcı" />
		<profile file="2" name="Başman+Sandallı" />
		<profile file="1" name="Joueur Humain" />
		<profile file="10" name="Göksay+Köse" />
		<profile file="30" name="Altay+Basaranoğlu" />
		<profile file="7" name="Cirit+Mutlu" />
		<profile file="6" name="Çamaş+Demirbaş" />
		<profile file="32" name="Çalışkan+Cap+Doğaner" />
		<profile file="5" name="Çağlayan+Elmas" />
		<profile file="31" name="Bilgin+Karabağ" />
		<profile file="4" name="Bingöl+Ketenci" />
		<profile file="9" name="Eren+Gökçe" />
		<profile file="8" name="Demirkol+Doğan" />
		<profile file="50" name="Promeneur 3" />
	</list>
</profiles>

