<?xml version="1.0" encoding="utf-8"?>
<animes xmlns:xsi="http://www.w3.org/2001/XMLSchema-instance" 
		xsi:noNamespaceSchemaLocation="..\..\..\..\xml\schemas\animes.xsd" 
		scale="1" default="walking" boundHeight="19" >
	<shadows folder="shadow">
		<shadow name="jumpShadow" file="shadow.gif" />
	</shadows>
	<gestures>
		<gesture name="bouncing" folder="jumping" shadow="jumpShadow" shadowYShift="-5">
			<direction name="down">
				<step file="down.gif" />
			</direction>
			<direction name="left">
				<step file="left.gif" />
			</direction>
			<direction name="right">
				<step file="right.gif" />
			</direction>
			<direction name="up">
				<step file="up.gif" />
			</direction>
		</gesture>
		<gesture name="burning" folder="burning">
			<direction name="none">
				<step duration="60" file="1.gif" />
				<step duration="60" file="2.gif" />
				<step duration="60" file="3.gif" />
				<step duration="80" file="4.gif" />
				<step duration="140" file="5.gif" />
			</direction>
		</gesture>
		<gesture name="carrying" folder="carrying" repeat="true">
			<direction name="down" folder="down">
				<step duration="50" file="lf1.gif" />
				<step duration="75" file="lf2.gif" />
				<step duration="75" file="lf3.gif" />
				<step duration="75" file="lf2.gif" />
				<step duration="50" file="lf1.gif" />
				<step duration="50" file="rf1.gif" />
				<step duration="75" file="rf2.gif" />
				<step duration="75" file="rf3.gif" />
				<step duration="75" file="rf2.gif" />
				<step duration="50" file="rf1.gif" />
			</direction>
			<direction name="left" folder="left">
				<step duration="50" file="lf1.gif" />
				<step duration="75" file="lf2.gif" />
				<step duration="75" file="lf3.gif" />
				<step duration="75" file="lf2.gif" />
				<step duration="50" file="lf1.gif" />
				<step duration="50" file="rf1.gif" />
				<step duration="75" file="rf2.gif" />
				<step duration="75" file="rf3.gif" />
				<step duration="75" file="rf2.gif" />
				<step duration="50" file="rf1.gif" />
			</direction>
			<direction name="right" folder="right">
				<step duration="50" file="lf1.gif" />
				<step duration="75" file="lf2.gif" />
				<step duration="75" file="lf3.gif" />
				<step duration="75" file="lf2.gif" />
				<step duration="50" file="lf1.gif" />
				<step duration="50" file="rf1.gif" />
				<step duration="75" file="rf2.gif" />
				<step duration="75" file="rf3.gif" />
				<step duration="75" file="rf2.gif" />
				<step duration="50" file="rf1.gif" />
			</direction>
			<direction name="up" folder="up">
				<step duration="50" file="lf1.gif" />
				<step duration="75" file="lf2.gif" />
				<step duration="75" file="lf3.gif" />
				<step duration="75" file="lf2.gif" />
				<step duration="50" file="lf1.gif" />
				<step duration="50" file="rf1.gif" />
				<step duration="75" file="rf2.gif" />
				<step duration="75" file="rf3.gif" />
				<step duration="75" file="rf2.gif" />
				<step duration="50" file="rf1.gif" />
			</direction>
		</gesture>
		<gesture name="holding" folder="holding">
			<direction name="down">
				<step file="down.gif" />
			</direction>
			<direction name="left">
				<step file="left.gif" />
			</direction>
			<direction name="right">
				<step file="right.gif" />
			</direction>
			<direction name="up">
				<step file="up.gif" />
			</direction>
		</gesture>
		<gesture name="jumping" folder="jumping" shadow="jumpShadow" >
			<direction name="down">
				<step file="down.gif" />
			</direction>
			<direction name="left">
				<step file="left.gif" />
			</direction>
			<direction name="right">
				<step file="right.gif" />
			</direction>
			<direction name="up">
				<step file="up.gif" />
			</direction>
		</gesture>
		<gesture name="landing" folder="jumping" shadow="jumpShadow" >
			<direction name="down">
				<step file="down.gif" />
			</direction>
			<direction name="left">
				<step file="left.gif" />
			</direction>
			<direction name="right">
				<step file="right.gif" />
			</direction>
			<direction name="up">
				<step file="up.gif" />
			</direction>
		</gesture>
		<gesture name="picking" folder="picking">
			<direction name="down">
				<step duration="150" file="down.gif" />
			</direction>
			<direction name="left">
				<step duration="150" file="left.gif" />
			</direction>
			<direction name="right">
				<step duration="150" file="right.gif" />
			</direction>
			<direction name="up">
				<step duration="150" file="up.gif" />
			</direction>
		</gesture>
		<gesture name="staggering" folder="staggering" repeat="true">
			<direction name="none">
				<step duration="100" file="center.gif" />
				<step duration="100" file="left1.gif" />
				<step duration="100" file="left2.gif" />
				<step duration="100" file="left1.gif" />
				<step duration="100" file="center.gif" />
				<step duration="100" file="right1.gif" />
				<step duration="100" file="right2.gif" />
				<step duration="100" file="right1.gif" />
			</direction>
		</gesture>
		<gesture name="standing" folder="standing">
			<direction name="down">
				<step file="down.gif" />
			</direction>
			<direction name="left">
				<step file="left.gif" />
			</direction>
			<direction name="right">
				<step file="right.gif" />
			</direction>
			<direction name="up">
				<step file="up.gif" />
			</direction>
		</gesture>
		<gesture name="waiting" folder="waiting" repeat="true">
			<direction name="none">
				<step duration="100" file="1.gif" />
				<step duration="250" file="2.gif" />
				<step duration="100" file="1.gif" />
				<step duration="250" file="3.gif" />
				<step duration="100" file="1.gif" />
				<step duration="250" file="2.gif" />
				<step duration="100" file="1.gif" />
				<step duration="250" file="3.gif" />
				<step duration="100" file="1.gif" />
				<step duration="250" file="2.gif" />
				<step duration="100" file="1.gif" />
				<step duration="250" file="3.gif" />
				<step duration="100" file="1.gif" />
				<step duration="250" file="2.gif" />
				<step duration="100" file="1.gif" />
				<step duration="250" file="3.gif" />
				<step duration="400" file="1.gif" />
				<step duration="100" file="4.gif" />
				<step duration="100" file="1.gif" />
				<step duration="100" file="4.gif" />
				<step duration="100" file="1.gif" />
				<step duration="100" file="4.gif" />
				<step duration="200" file="1.gif" />
				<step duration="100" file="5.gif" />
				<step duration="100" file="6.gif" />
				<step duration="100" file="7.gif" />
				<step duration="100" file="6.gif" />
				<step duration="100" file="7.gif" />
				<step duration="100" file="6.gif" />
				<step duration="100" file="7.gif" />
				<step duration="100" file="6.gif" />
				<step duration="100" file="7.gif" />
				<step duration="100" file="6.gif" />
				<step duration="100" file="7.gif" />
				<step duration="100" file="6.gif" />
				<step duration="100" file="7.gif" />
				<step duration="100" file="5.gif" />
				<step duration="300" file="1.gif" />
			</direction>
		</gesture>
		<gesture name="walking" folder="walking" repeat="true">
			<direction name="down" folder="down">
				<step duration="50" file="lf1.gif" />
				<step duration="75" file="lf2.gif" />
				<step duration="75" file="lf3.gif" />
				<step duration="75" file="lf2.gif" />
				<step duration="50" file="lf1.gif" />
				<step duration="50" file="rf1.gif" />
				<step duration="75" file="rf2.gif" />
				<step duration="75" file="rf3.gif" />
				<step duration="75" file="rf2.gif" />
				<step duration="50" file="rf1.gif" />
			</direction>
			<direction name="left" folder="left">
				<step duration="50" file="lf1.gif" />
				<step duration="75" file="lf2.gif" />
				<step duration="75" file="lf3.gif" />
				<step duration="75" file="lf2.gif" />
				<step duration="50" file="lf1.gif" />
				<step duration="50" file="rf1.gif" />
				<step duration="75" file="rf2.gif" />
				<step duration="75" file="rf3.gif" />
				<step duration="75" file="rf2.gif" />
				<step duration="50" file="rf1.gif" />
			</direction>
			<direction name="right" folder="right">
				<step duration="50" file="lf1.gif" />
				<step duration="75" file="lf2.gif" />
				<step duration="75" file="lf3.gif" />
				<step duration="75" file="lf2.gif" />
				<step duration="50" file="lf1.gif" />
				<step duration="50" file="rf1.gif" />
				<step duration="75" file="rf2.gif" />
				<step duration="75" file="rf3.gif" />
				<step duration="75" file="rf2.gif" />
				<step duration="50" file="rf1.gif" />
			</direction>
			<direction name="up" folder="up">
				<step duration="50" file="lf1.gif" />
				<step duration="75" file="lf2.gif" />
				<step duration="75" file="lf3.gif" />
				<step duration="75" file="lf2.gif" />
				<step duration="50" file="lf1.gif" />
				<step duration="50" file="rf1.gif" />
				<step duration="75" file="rf2.gif" />
				<step duration="75" file="rf3.gif" />
				<step duration="75" file="rf2.gif" />
				<step duration="50" file="rf1.gif" />
			</direction>
		</gesture>
		<gesture name="winning" folder="winning" repeat="true">
			<direction name="none">
				<step duration="250" file="1.gif" />
				<step duration="50" file="2.gif" />
				<step duration="50" file="3.gif" />
				<step duration="50" file="4.gif" />
				<step duration="50" file="3.gif" />
				<step duration="50" file="2.gif" />
			</direction>
		</gesture>
	</gestures>		
</animes>
