<?xml version="1.0" encoding="utf-8"?>
<abilities xmlns:xsi="http://www.w3.org/2001/XMLSchema-instance" 
		xsi:noNamespaceSchemaLocation="../../../../schemas/abilities.xsd" >

		<!-- STATE -->
<!-- 	SPRITE_ENTRY_DURATION --> 
		<ability strength="1000" frame="false" time="-1" uses="-1">
			<name value="SPRITE_ENTRY_DURATION" />
		</ability>
<!-- 	SPRITE_MOVE_ASSISTANCE -->
		<ability strength="0.33" frame="false" time="-1" uses="-1">
			<name value="SPRITE_MOVE_ASSISTANCE"/>
		</ability>
<!-- 	SPRITE_TRAVERSE_ITEM -->
		<ability strength="1" frame="false" time="-1" uses="-1">
			<name value="SPRITE_TRAVERSE_ITEM"/>
		</ability>
<!--  	HERO_BOMB_DROP_LATENCY --> 
		<ability strength="100" frame="false" time="-1" uses="-1">
			<name value="HERO_BOMB_DROP_LATENCY" />
		</ability>		
<!--  	HERO_BOMB_NUMBER_MAX --> 
		<ability strength="10" frame="false" time="-1" uses="-1">
			<name value="HERO_BOMB_NUMBER_MAX" />
		</ability>
<!--  	HERO_BOMB_RANGE_MAX --> 
		<ability strength="10" frame="false" time="-1" uses="-1">
			<name value="HERO_BOMB_NUMBER_MAX" />
		</ability>
<!--  	HERO_BOMB_RANGE_MAX --> 
		<ability strength="10" frame="false" time="-1" uses="-1">
			<name value="HERO_BOMB_RANGE_MAX" />
		</ability>
<!--  	HERO_BOMB_TIMER_COEFFICIENT --> 
		<ability strength="1" frame="false" time="-1" uses="-1">
			<name value="HERO_BOMB_TIMER_COEFFICIENT" />
		</ability>
<!--  	HERO_CELEBRATION_DURATION --> 
		<ability strength="4000" frame="false" time="-1" uses="-1">
			<name value="HERO_CELEBRATION_DURATION" />
		</ability>
<!--  	HERO_PUNCH_DURATION --> 
		<ability strength="230" frame="false" time="-1" uses="-1">
			<name value="HERO_PUNCH_DURATION" />
		</ability>
<!--  	HERO_REBIRTH_DELAY --> 
		<ability strength="500" frame="false" time="-1" uses="-1">
			<name value="HERO_REBIRTH_DELAY" />
		</ability>
<!--  	HERO_REBIRTH_DURATION --> 
		<ability strength="3000" frame="false" time="-1" uses="-1">
			<name value="HERO_REBIRTH_DURATION" />
		</ability>
<!--  	HERO_WAIT_DURATION --> 
		<ability strength="4000" frame="false" time="-1" uses="-1">
			<name value="HERO_WAIT_DURATION" />
		</ability>
<!--  	HERO_WALK_SPEED --> 
		<ability strength="0.42" frame="false" time="-1" uses="-1">
			<name value="HERO_WALK_SPEED_M1" />
		</ability>
		<ability strength="1.28" frame="false" time="-1" uses="-1">
			<name value="HERO_WALK_SPEED_P1" />
		</ability>
		<ability strength="1.51" frame="false" time="-1" uses="-1">
			<name value="HERO_WALK_SPEED_P2" />
		</ability>
		<ability strength="1.75" frame="false" time="-1" uses="-1">
			<name value="HERO_WALK_SPEED_P3" />
		</ability>
		<ability strength="2.03" frame="false" time="-1" uses="-1">
			<name value="HERO_WALK_SPEED_P4" />
		</ability>
		<ability strength="4.12" frame="false" time="-1" uses="-1">
			<name value="HERO_WALK_SPEED_P99" />
		</ability>
			
		<!-- ACTION -->
<!--  	APPEAR --> 
		<ability strength="1" frame="false" time="-1" uses="-1">
			<action name="APPEAR" contact="NONE" direction="ANY"
				orientation="NONE" target="NONE" tilePosition="NONE" />
		</ability>
<!--  	CRY --> 
		<ability strength="1" frame="false" time="-1" uses="-1">
			<action name="CRY" contact="NONE" direction="ANY"
				orientation="NONE" target="NONE" tilePosition="NONE" />
		</ability>
<!--  	DROP --> 
		<ability strength="1" frame="false" time="-1" uses="-1">
			<action name="DROP" contact="ANY" direction="ANY"
				orientation="ANY" target="BOMB" tilePosition="ANY" />
		</ability>
<!--  	EXULT --> 
		<ability strength="1" frame="false" time="-1" uses="-1">
			<action name="EXULT" contact="NONE" direction="ANY"
				orientation="NONE" target="NONE" tilePosition="NONE" />
		</ability>
<!--  	GATHER --> 
		<ability strength="1" frame="false" time="-1" uses="-1">
			<action name="GATHER" contact="ANY" direction="ANY"
				orientation="ANY" target="ITEM" tilePosition="SAME" />
		</ability>
<!--  	JUMP --> 
		<ability strength="1" frame="false" time="-1" uses="-1">
			<action name="JUMP" contact="NONE" direction="ANY"
				orientation="NONE" target="NONE" tilePosition="NONE" />
		</ability>
<!--  	LAND --> 
		<ability strength="1" frame="false" time="-1" uses="-1">
			<action name="LAND" contact="NONE" direction="ANY"
				orientation="NONE" target="NONE" tilePosition="NONE" />
		</ability>
<!--  	MOVEHIGH --> 
		<ability strength="1" frame="false" time="-1" uses="-1">
			<action name="MOVEHIGH" contact="NONE" direction="ANY"
				orientation="NONE" target="NONE" tilePosition="NONE" />
		</ability>
<!--  	MOVELOW --> 
		<ability strength="1" frame="false" time="-1" uses="-1">
			<action name="MOVELOW" contact="NONE" direction="ANY"
				orientation="NONE" target="NONE" tilePosition="NONE" />
		</ability>
<!--  	RELEASE --> 
		<ability strength="1" frame="false" time="-1" uses="-1">
			<action name="RELEASE" contact="ANY" direction="ANY"
				orientation="ANY" target="ITEM" tilePosition="ANY" />
		</ability>
<!--  	TRANSMIT --> 
		<ability strength="1" frame="false" time="-1" uses="-1">
			<action name="TRANSMIT" contact="INTERSECTION" direction="ANY"
				orientation="ANY" target="HERO" tilePosition="ANY" />
		</ability>
<!--  	TRIGGER --> 
		<ability strength="1" frame="false" time="-1" uses="-1">
			<action name="TRIGGER" contact="ANY" direction="ANY"
				orientation="ANY" target="BOMB" tilePosition="ANY" />
		</ability>

</abilities>
