<?xml version="1.0" encoding="UTF-8"?>
<zone xmlns:xsi="http://www.w3.org/2001/XMLSchema-instance" xsi:noNamespaceSchemaLocation="..\..\..\..\resources\schemas\zone.xsd">
	<variableTiles>
		<variableTile name="itemTile">
			<value proba="0.4000000059604645">
				<item name="extrabomb" />
			</value>
			<value proba="0.6000000238418579">
				<item name="extraflame" />
			</value>
		</variableTile>
		<variableTile name="blockTile">
			<value proba="0.25">
				<block group="softwalls" name="redyellow" />
				<item name="extrabomb" />
			</value>
			<value proba="0.25">
				<block group="softwalls" name="yellowred" />
				<item name="extrabomb" />
			</value>
			<value proba="0.25">
				<block group="softwalls" name="redyellow" />
				<item name="extraflame" />
			</value>
			<value proba="0.25">
				<block group="softwalls" name="yellowred" />
				<item name="extraflame" />
			</value>
		</variableTile>
	</variableTiles>
	<matrix>
		<line pos="0">
			<tile pos="0">
				<floor name="regular" />
			</tile>
			<tile pos="1">
				<floor name="regular" />
			</tile>
			<tile pos="2">
				<floor name="regular" />
			</tile>
			<tile pos="3">
				<floor name="regular" />
			</tile>
			<tile pos="4">
				<floor name="regular" />
			</tile>
			<tile pos="5">
				<floor name="regular" />
			</tile>
			<tile pos="6">
				<floor name="regular" />
			</tile>
			<tile pos="7">
				<floor name="regular" />
			</tile>
			<tile pos="8">
				<floor name="regular" />
			</tile>
			<tile pos="9">
				<floor name="regular" />
			</tile>
			<tile pos="10">
				<floor name="regular" />
			</tile>
		</line>
		<line pos="1">
			<tile pos="0">
				<floor name="regular" />
			</tile>
			<tile pos="1">
				<floor name="regular" />
			</tile>
			<tile pos="2">
				<floor name="regular" />
			</tile>
			<tile pos="3">
				<floor name="regular" />
			</tile>
			<tile pos="4">
				<floor name="regular" />
				<block group="hardwalls" name="regular" />
			</tile>
			<tile pos="5">
				<floor name="regular" />
				<block group="hardwalls" name="regular" />
			</tile>
			<tile pos="6">
				<floor name="regular" />
				<block group="hardwalls" name="regular" />
			</tile>
			<tile pos="7">
				<floor name="regular" />
			</tile>
			<tile pos="8">
				<floor name="regular" />
			</tile>
			<tile pos="9">
				<floor name="regular" />
			</tile>
			<tile pos="10">
				<floor name="regular" />
			</tile>
		</line>
		<line pos="2">
			<tile pos="0">
				<floor name="regular" />
			</tile>
			<tile pos="1">
				<floor name="regular" />
			</tile>
			<tile pos="2">
				<floor name="regular" />
			</tile>
			<tile pos="3">
				<floor name="regular" />
			</tile>
			<tile pos="4">
				<floor name="regular" />
				<block group="hardwalls" name="regular" />
			</tile>
			<tile pos="5">
				<floor name="regular" />
				<reference name="itemTile" />
			</tile>
			<tile pos="6">
				<floor name="regular" />
				<block group="hardwalls" name="regular" />
			</tile>
			<tile pos="7">
				<floor name="regular" />
			</tile>
			<tile pos="8">
				<floor name="regular" />
			</tile>
			<tile pos="9">
				<floor name="regular" />
			</tile>
			<tile pos="10">
				<floor name="regular" />
			</tile>
		</line>
		<line pos="3">
			<tile pos="0">
				<floor name="regular" />
			</tile>
			<tile pos="1">
				<floor name="regular" />
			</tile>
			<tile pos="2">
				<floor name="regular" />
			</tile>
			<tile pos="3">
				<floor name="regular" />
			</tile>
			<tile pos="4">
				<floor name="regular" />
				<block group="hardwalls" name="regular" />
			</tile>
			<tile pos="5">
				<floor name="regular" />
			</tile>
			<tile pos="6">
				<floor name="regular" />
				<block group="hardwalls" name="regular" />
			</tile>
			<tile pos="7">
				<floor name="regular" />
			</tile>
			<tile pos="8">
				<floor name="regular" />
			</tile>
			<tile pos="9">
				<floor name="regular" />
			</tile>
			<tile pos="10">
				<floor name="regular" />
			</tile>
		</line>
		<line pos="4">
			<tile pos="0">
				<floor name="regular" />
			</tile>
			<tile pos="1">
				<floor name="regular" />
				<block group="hardwalls" name="regular" />
			</tile>
			<tile pos="2">
				<floor name="regular" />
				<block group="hardwalls" name="regular" />
			</tile>
			<tile pos="3">
				<floor name="regular" />
				<block group="hardwalls" name="regular" />
			</tile>
			<tile pos="4">
				<floor name="regular" />
				<block group="hardwalls" name="regular" />
			</tile>
			<tile pos="5">
				<floor name="regular" />
			</tile>
			<tile pos="6">
				<floor name="regular" />
				<block group="hardwalls" name="regular" />
			</tile>
			<tile pos="7">
				<floor name="regular" />
				<block group="hardwalls" name="regular" />
			</tile>
			<tile pos="8">
				<floor name="regular" />
				<block group="hardwalls" name="regular" />
			</tile>
			<tile pos="9">
				<floor name="regular" />
				<block group="hardwalls" name="regular" />
			</tile>
			<tile pos="10">
				<floor name="regular" />
			</tile>
		</line>
		<line pos="5">
			<tile pos="0">
				<floor name="regular" />
			</tile>
			<tile pos="1">
				<floor name="regular" />
				<block group="hardwalls" name="regular" />
			</tile>
			<tile pos="2">
				<floor name="regular" />
				<reference name="itemTile" />
			</tile>
			<tile pos="3">
				<floor name="regular" />
			</tile>
			<tile pos="4">
				<floor name="regular" />
			</tile>
			<tile pos="5">
				<floor name="regular" />
				<reference name="blockTile" />
			</tile>
			<tile pos="6">
				<floor name="regular" />
			</tile>
			<tile pos="7">
				<floor name="regular" />
			</tile>
			<tile pos="8">
				<floor name="regular" />
				<reference name="itemTile" />
			</tile>
			<tile pos="9">
				<floor name="regular" />
				<block group="hardwalls" name="regular" />
			</tile>
			<tile pos="10">
				<floor name="regular" />
			</tile>
		</line>
		<line pos="6">
			<tile pos="0">
				<floor name="regular" />
			</tile>
			<tile pos="1">
				<floor name="regular" />
				<block group="hardwalls" name="regular" />
			</tile>
			<tile pos="2">
				<floor name="regular" />
				<block group="hardwalls" name="regular" />
			</tile>
			<tile pos="3">
				<floor name="regular" />
				<block group="hardwalls" name="regular" />
			</tile>
			<tile pos="4">
				<floor name="regular" />
				<block group="hardwalls" name="regular" />
			</tile>
			<tile pos="5">
				<floor name="regular" />
			</tile>
			<tile pos="6">
				<floor name="regular" />
				<block group="hardwalls" name="regular" />
			</tile>
			<tile pos="7">
				<floor name="regular" />
				<block group="hardwalls" name="regular" />
			</tile>
			<tile pos="8">
				<floor name="regular" />
				<block group="hardwalls" name="regular" />
			</tile>
			<tile pos="9">
				<floor name="regular" />
				<block group="hardwalls" name="regular" />
			</tile>
			<tile pos="10">
				<floor name="regular" />
			</tile>
		</line>
		<line pos="7">
			<tile pos="0">
				<floor name="regular" />
			</tile>
			<tile pos="1">
				<floor name="regular" />
			</tile>
			<tile pos="2">
				<floor name="regular" />
			</tile>
			<tile pos="3">
				<floor name="regular" />
			</tile>
			<tile pos="4">
				<floor name="regular" />
				<block group="hardwalls" name="regular" />
			</tile>
			<tile pos="5">
				<floor name="regular" />
			</tile>
			<tile pos="6">
				<floor name="regular" />
				<block group="hardwalls" name="regular" />
			</tile>
			<tile pos="7">
				<floor name="regular" />
			</tile>
			<tile pos="8">
				<floor name="regular" />
			</tile>
			<tile pos="9">
				<floor name="regular" />
			</tile>
			<tile pos="10">
				<floor name="regular" />
			</tile>
		</line>
		<line pos="8">
			<tile pos="0">
				<floor name="regular" />
			</tile>
			<tile pos="1">
				<floor name="regular" />
			</tile>
			<tile pos="2">
				<floor name="regular" />
			</tile>
			<tile pos="3">
				<floor name="regular" />
			</tile>
			<tile pos="4">
				<floor name="regular" />
				<block group="hardwalls" name="regular" />
			</tile>
			<tile pos="5">
				<floor name="regular" />
				<reference name="itemTile" />
			</tile>
			<tile pos="6">
				<floor name="regular" />
				<block group="hardwalls" name="regular" />
			</tile>
			<tile pos="7">
				<floor name="regular" />
			</tile>
			<tile pos="8">
				<floor name="regular" />
			</tile>
			<tile pos="9">
				<floor name="regular" />
			</tile>
			<tile pos="10">
				<floor name="regular" />
			</tile>
		</line>
		<line pos="9">
			<tile pos="0">
				<floor name="regular" />
			</tile>
			<tile pos="1">
				<floor name="regular" />
			</tile>
			<tile pos="2">
				<floor name="regular" />
			</tile>
			<tile pos="3">
				<floor name="regular" />
			</tile>
			<tile pos="4">
				<floor name="regular" />
				<block group="hardwalls" name="regular" />
			</tile>
			<tile pos="5">
				<floor name="regular" />
				<block group="hardwalls" name="regular" />
			</tile>
			<tile pos="6">
				<floor name="regular" />
				<block group="hardwalls" name="regular" />
			</tile>
			<tile pos="7">
				<floor name="regular" />
			</tile>
			<tile pos="8">
				<floor name="regular" />
			</tile>
			<tile pos="9">
				<floor name="regular" />
			</tile>
			<tile pos="10">
				<floor name="regular" />
			</tile>
		</line>
		<line pos="10">
			<tile pos="0">
				<floor name="regular" />
			</tile>
			<tile pos="1">
				<floor name="regular" />
			</tile>
			<tile pos="2">
				<floor name="regular" />
			</tile>
			<tile pos="3">
				<floor name="regular" />
			</tile>
			<tile pos="4">
				<floor name="regular" />
			</tile>
			<tile pos="5">
				<floor name="regular" />
			</tile>
			<tile pos="6">
				<floor name="regular" />
			</tile>
			<tile pos="7">
				<floor name="regular" />
			</tile>
			<tile pos="8">
				<floor name="regular" />
			</tile>
			<tile pos="9">
				<floor name="regular" />
			</tile>
			<tile pos="10">
				<floor name="regular" />
			</tile>
		</line>
	</matrix>
</zone>

