<?xml version="1.0" encoding="UTF-8"?>
<points
	xmlns:xsi="http://www.w3.org/2001/XMLSchema-instance" 
	xsi:noNamespaceSchemaLocation="../../../../schemas/point.xsd">
	
	<notes>
		<line value="Les points sont donnés directement en fonction du rang des joueurs." />
		<line value="Ce rang dépend de la somme des points marqués à chaque manche."/>
		<line value="Les scores sont considérés comme critères secondaires."/>
		<line value="Remarque: pour une rencontre décisive, il n'y a, a priori, qu'une seule manche."/>
	</notes>

	<rankings invert="true">
		<total />
		<scores type="bombings"/>
		<scores type="items"/>
		<scores type="bombs"/>
	</rankings>	
 		
</points>
